imglyb_examples/__init__.py
imglyb_examples/bdv_hello_world.py
imglyb_examples/bdv_painter.py
imglyb_examples/butterfly.py
imglyb_examples/qt_awt.py
imglyb_examples/version_info.py
imglyb_examples/views_stack.py
imglyb_examples-0.1.0.dist-info/METADATA
imglyb_examples-0.1.0.dist-info/WHEEL
imglyb_examples-0.1.0.dist-info/entry_points.txt
imglyb_examples-0.1.0.dist-info/top_level.txt
imglyb_examples-0.1.0.dist-info/RECORD
