Metadata-Version: 2.1
Name: imglyb-examples
Version: 0.1.0
Summary: Examples for imglyb.
Home-page: https://github.com/hanslovsky/imglyb-examples
Author: Philipp Hanslovsky
Author-email: hanslovskyp@janelia.hhmi.org
License: UNKNOWN
Platform: UNKNOWN
Requires-Python: >=3
